kiro_cli_mcp/__init__.py
kiro_cli_mcp/__main__.py
kiro_cli_mcp/config.py
kiro_cli_mcp/errors.py
kiro_cli_mcp/executor.py
kiro_cli_mcp/models.py
kiro_cli_mcp/process_pool.py
kiro_cli_mcp/resources.py
kiro_cli_mcp/server.py
kiro_cli_mcp/session.py
kiro_cli_mcp/streaming.py
kiro_cli_mcp/tools.py
kiro_cli_mcp-0.1.0.dist-info/METADATA
kiro_cli_mcp-0.1.0.dist-info/WHEEL
kiro_cli_mcp-0.1.0.dist-info/entry_points.txt
kiro_cli_mcp-0.1.0.dist-info/licenses/LICENSE
kiro_cli_mcp-0.1.0.dist-info/RECORD
