Metadata-Version: 2.4
Name: kiro-cli-mcp
Version: 0.1.0
Summary: MCP Server for orchestrating Kiro CLI from Kiro IDE
Project-URL: Homepage, https://github.com/vanphappi/kiro-cli-mcp
Project-URL: Repository, https://github.com/vanphappi/kiro-cli-mcp
Project-URL: Issues, https://github.com/vanphappi/kiro-cli-mcp/issues
Project-URL: Documentation, https://github.com/vanphappi/kiro-cli-mcp#readme
Author-email: Kiro CLI MCP Contributors <contributors@kiro-cli-mcp.dev>
License-Expression: MIT
License-File: LICENSE
Keywords: ai,assistant,cli,kiro,mcp
Classifier: Development Status :: 3 - Alpha
Classifier: Intended Audience :: Developers
Classifier: License :: OSI Approved :: MIT License
Classifier: Programming Language :: Python :: 3
Classifier: Programming Language :: Python :: 3.10
Classifier: Programming Language :: Python :: 3.11
Classifier: Programming Language :: Python :: 3.12
Requires-Python: >=3.10
Requires-Dist: mcp>=1.0.0
Requires-Dist: pydantic>=2.0.0
Provides-Extra: dev
Requires-Dist: hypothesis>=6.100.0; extra == 'dev'
Requires-Dist: mypy>=1.0.0; extra == 'dev'
Requires-Dist: pytest-asyncio>=0.23.0; extra == 'dev'
Requires-Dist: pytest-cov>=4.0.0; extra == 'dev'
Requires-Dist: pytest>=8.0.0; extra == 'dev'
Requires-Dist: ruff>=0.1.0; extra == 'dev'
